multiply_application/__init__.py
multiply_application/multiplication.py
multiply_application-0.1.0.dist-info/METADATA
multiply_application-0.1.0.dist-info/WHEEL
multiply_application-0.1.0.dist-info/top_level.txt
multiply_application-0.1.0.dist-info/RECORD
